resolver/__init__.py
resolver/request.py
sceptre_request_resolver-0.4.0.dist-info/entry_points.txt
sceptre_request_resolver-0.4.0.dist-info/WHEEL
sceptre_request_resolver-0.4.0.dist-info/METADATA
sceptre_request_resolver-0.4.0.dist-info/RECORD
