Metadata-Version: 2.1
Name: sceptre-request-resolver
Version: 0.4.0
Summary: A Sceptre resolver to make requests from REST API endpoints
Home-page: https://github.com/Sceptre/sceptre-request-resolver
License: Apache-2.0
Keywords: sceptre,sceptre-resolver
Author: Khai Do
Author-email: zaro0508@gmail.com
Requires-Python: >=3.8,<3.12
Classifier: Environment :: Console
Classifier: Intended Audience :: Developers
Classifier: License :: OSI Approved :: Apache Software License
Classifier: Natural Language :: English
Classifier: Programming Language :: Python :: 3
Classifier: Programming Language :: Python :: 3.8
Classifier: Programming Language :: Python :: 3.9
Classifier: Programming Language :: Python :: 3.10
Classifier: Programming Language :: Python :: 3.11
Classifier: Programming Language :: Python :: 3.10
Classifier: Programming Language :: Python :: 3.11
Classifier: Programming Language :: Python :: 3.8
Classifier: Programming Language :: Python :: 3.9
Requires-Dist: jsonschema (>=3.2.0,<4.0.0)
Requires-Dist: requests (>=2.28.2,<3.0.0)
Requires-Dist: validator-collection (>=1.5.0,<2.0.0)
Project-URL: Repository, https://github.com/Sceptre/sceptre-request-resolver
